fabsetup/__init__.py
fabsetup/__main__.py
fabsetup/_version.py
fabsetup/addons.py
fabsetup/fabfile.py
fabsetup/main.py
fabsetup/print.py
fabsetup/task.py
fabsetup/fabfile-data/files/home/USERNAME/.fabsetup-addon-repos/fabsetup-USER-ADDON/README.md
fabsetup/fabfile-data/files/home/USERNAME/.fabsetup-addon-repos/fabsetup-USER-ADDON/fabsetup_USER_TASK/__init__.py.template
fabsetup/fabfile-data/files/home/USERNAME/.fabsetup-addon-repos/fabsetup-USER-ADDON/fabsetup_USER_TASK/_version.py
fabsetup/fabutils/__init__.py
fabsetup/fabutils/addon.py
fabsetup/fabutils/queries.py
fabsetup/utils/__init__.py
fabsetup/utils/colors.py
fabsetup/utils/decorate.py
fabsetup/utils/decorators.py
fabsetup/utils/docstring.py
fabsetup/utils/outfile.py
fabsetup/utils/pandoc.py
fabsetup/utils/css/html-script.js
fabsetup/utils/css/outfile.css
fabsetup/utils/pandoc-filter/fenced-raw-codeblock.lua
fabsetup-0.14.0.dist-info/LICENSE.txt
fabsetup-0.14.0.dist-info/METADATA
fabsetup-0.14.0.dist-info/WHEEL
fabsetup-0.14.0.dist-info/entry_points.txt
fabsetup-0.14.0.dist-info/top_level.txt
fabsetup-0.14.0.dist-info/RECORD
