Metadata-Version: 2.1
Name: fabsetup
Version: 0.14.0
Summary: Summary: fabric-2 setup scripts and fabric utils library
Home-page: https://github.com/theno/fabsetup
Author: Theodor Nolte
Author-email: fabsetup@theno.eu
License: MIT
Keywords: python development utilities library
Classifier: Development Status :: 3 - Alpha
Classifier: Intended Audience :: Developers
Classifier: Topic :: Software Development :: Libraries :: Python Modules
Classifier: License :: OSI Approved :: MIT License
Classifier: Programming Language :: Python :: 3
Classifier: Programming Language :: Python :: 3.5
Classifier: Programming Language :: Python :: 3.6
Classifier: Programming Language :: Python :: 3.7
Classifier: Programming Language :: Python :: 3.8
Classifier: Programming Language :: Python :: 3.9
Classifier: Programming Language :: Python :: 3.10
License-File: LICENSE.txt
Requires-Dist: fabric (>=2.0.0)
Provides-Extra: devel
Requires-Dist: black ; extra == 'devel'
Requires-Dist: mutmut ; extra == 'devel'
Requires-Dist: pytest ; extra == 'devel'
Requires-Dist: recommonmark ; extra == 'devel'
Requires-Dist: sphinx ; extra == 'devel'
Requires-Dist: tox ; extra == 'devel'
